LICENSE
MANIFEST.in
README.rst
setup.cfg
setup.py
version.py
examples/db-cluster/README.rst
examples/db-cluster/inst-db-cluster.sh
examples/db-cluster/network.dot
examples/db-cluster/plugin.py
examples/db-cluster/report.txt
examples/db-cluster/report_plugin.py
examples/db-cluster/tables.sql
examples/db-cluster/tables2.sql
examples/hello/hello/hello.txt
examples/hello/hello/plugin.py
examples/puppet/inst-puppet.sh
examples/puppet/ec2-deb6/deb6-upgrade.sh
examples/puppet/ec2-deb6/plugin.py
examples/puppet/puppet-agent/inst-puppet-agent.sh
examples/puppet/puppet-agent/plugin.py
examples/puppet/puppet-master/inst-puppet-master.sh
examples/puppet/puppet-master/plugin.py
examples/puppet/puppet-master/site.pp
poni/__init__.py
poni/cloud.py
poni/colors.py
poni/config.py
poni/core.py
poni/errors.py
poni/importer.py
poni/listout.py
poni/newconfig.py
poni/rcontrol.py
poni/rcontrol_all.py
poni/rcontrol_openssh.py
poni/rcontrol_paramiko.py
poni/recode.py
poni/times.py
poni/tool.py
poni/util.py
poni/vc.py
poni/version.py
poni/work.py
poni.egg-info/PKG-INFO
poni.egg-info/SOURCES.txt
poni.egg-info/dependency_links.txt
poni.egg-info/entry_points.txt
poni.egg-info/not-zip-safe
poni.egg-info/requires.txt
poni.egg-info/top_level.txt
tests/helper.py
tests/test_cmd_basic.py
tests/test_control.py
tests/test_settings.py
tests/test_templates.py
tests/test_times.py
tests/test_vc.py